ChatAIAgent.py
__init__.py
chatai_agent-1.1.2.dist-info/LICENSE
chatai_agent-1.1.2.dist-info/METADATA
chatai_agent-1.1.2.dist-info/WHEEL
chatai_agent-1.1.2.dist-info/top_level.txt
chatai_agent-1.1.2.dist-info/RECORD
