Metadata-Version: 2.1
Name: chatai-agent
Version: 1.1.2
Summary: Send messages to ChatGPT and get answers conveniently.
Home-page: https://github.com/GeneralYadoc/ChatAIAgent
Author: General Yadoc
Author-email: 133023047+GeneralYadoc@users.noreply.github.com
License: MIT
Platform: UNKNOWN
Classifier: Development Status :: 4 - Beta
Classifier: Programming Language :: Python
Classifier: Programming Language :: Python :: 3.7
Classifier: Programming Language :: Python :: 3.8
Classifier: Programming Language :: Python :: 3.9
Classifier: License :: OSI Approved :: MIT License
License-File: LICENSE
Requires-Dist: openai (==0.27.5)
